event_emitter/__init__.py
event_emitter/event.py
event_emitter_js-0.1.2.dist-info/DESCRIPTION.rst
event_emitter_js-0.1.2.dist-info/METADATA
event_emitter_js-0.1.2.dist-info/RECORD
event_emitter_js-0.1.2.dist-info/WHEEL
event_emitter_js-0.1.2.dist-info/metadata.json
event_emitter_js-0.1.2.dist-info/top_level.txt
