Metadata-Version: 1.0
Name: event-emitter-js
Version: 0.1.2
Summary: JavaScript-like EventEmitter class for Python 3
Home-page: https://github.com/thiagodk/python-event-emitter
Author: Thiago Costa
Author-email: admin@rootbsd.info
License: UNKNOWN
Platform: UNKNOWN
